vera/__init__.py
vera/annotate.py
vera/embedding.py
vera/graph.py
vera/label_placement.py
vera/metrics.py
vera/overlap_computations.py
vera/plotting.py
vera/preprocessing.py
vera/region.py
vera/region_annotation.py
vera/rules.py
vera/utils.py
vera/variables.py
vera_explain-1.0.0.dist-info/licenses/LICENSE
vera_explain-1.0.0.dist-info/METADATA
vera_explain-1.0.0.dist-info/WHEEL
vera_explain-1.0.0.dist-info/top_level.txt
vera_explain-1.0.0.dist-info/RECORD
