Metadata-Version: 2.4
Name: vera-explain
Version: 1.0.0
Home-page: https://github.com/pavlin-policar/vera
Author: Pavlin G. Poličar
Author-email: pavlin.g.p@gmail.com
License: BSD 3-Clause License
Classifier: Development Status :: 4 - Beta
Classifier: Intended Audience :: Science/Research
Classifier: Intended Audience :: Developers
Classifier: Programming Language :: Python :: 3
Classifier: License :: OSI Approved :: BSD License
Classifier: Topic :: Scientific/Engineering
Classifier: Topic :: Scientific/Engineering :: Artificial Intelligence
Classifier: Topic :: Scientific/Engineering :: Bio-Informatics
Classifier: Topic :: Scientific/Engineering :: Visualization
License-File: LICENSE
Requires-Dist: numpy
Requires-Dist: pandas
Requires-Dist: scipy
Requires-Dist: scikit-learn
Requires-Dist: KDEpy
Requires-Dist: contourpy
Requires-Dist: shapely
Requires-Dist: matplotlib
Requires-Dist: glasbey
Dynamic: license-file
